stock_analysis/__init__.py
stock_analysis/stock_analysis_trends.py
stock_analysis_trends-0.0.12.dist-info/METADATA
stock_analysis_trends-0.0.12.dist-info/WHEEL
stock_analysis_trends-0.0.12.dist-info/top_level.txt
stock_analysis_trends-0.0.12.dist-info/RECORD
