Metadata-Version: 2.1
Name: stock-analysis-trends
Version: 0.0.12
Summary: Perform stock analysis on Indian and American stocks
Author: Arjun P
Author-email: <arjunprakash027@gmail.com>
Keywords: python,stock,bullish,bearish,analysis,stockmarket
Classifier: Development Status :: 1 - Planning
Classifier: Intended Audience :: Developers
Classifier: Programming Language :: Python :: 3
Classifier: Operating System :: Unix
Classifier: Operating System :: MacOS :: MacOS X
Classifier: Operating System :: Microsoft :: Windows
Requires-Dist: yahoofinancials
